{
  "BB01": {
    "id": "BB01",
    "descriptor": "Jenkins_2023_USA",
    "summary": null,
    "translation": null,
    "pdf": "QT001_Jenkins_2023_USA_SanDiego.pdf",
    "pdf_path": "02_Papers-goc/11-bai-ban-dau-va-mo-rong/QT001_Jenkins_2023_USA_SanDiego.pdf",
    "topic": "Anxiety epidemiology - USA (San Diego)",
    "set": "11-bai-ban-dau-va-mo-rong",
    "added": "2026-06-07",
    "note": "Bộ 11 bài ban đầu + mở rộng cho LA NCS Công Thị Hằng"
  },
  "BB02": {
    "id": "BB02",
    "descriptor": "Bhardwaj_2020_India",
    "summary": null,
    "translation": null,
    "pdf": "_MISLABELED_QT002_Saikia_actually_Bhardwaj_2020.pdf",
    "pdf_path": "02_Papers-goc/11-bai-ban-dau-va-mo-rong/_MISLABELED_QT002_Saikia_actually_Bhardwaj_2020.pdf",
    "topic": "Anxiety epidemiology - India (Chandigarh) - filename mislabeled, actual author Bhardwaj 2020",
    "set": "11-bai-ban-dau-va-mo-rong",
    "added": "2026-06-07",
    "note": "Bộ 11 bài ban đầu + mở rộng cho LA NCS Công Thị Hằng"
  },
  "BB03": {
    "id": "BB03",
    "descriptor": "Mandaknalli_Malusare_2021",
    "summary": null,
    "translation": null,
    "pdf": "03_Mandaknalli_Malusare_2021.pdf",
    "pdf_path": "02_Papers-goc/11-bai-ban-dau-va-mo-rong/03_Mandaknalli_Malusare_2021.pdf",
    "topic": "Anxiety / mental health - India",
    "set": "11-bai-ban-dau-va-mo-rong",
    "added": "2026-06-07",
    "note": "Bộ 11 bài ban đầu + mở rộng cho LA NCS Công Thị Hằng"
  },
  "BB05": {
    "id": "BB05",
    "descriptor": "Alharbi_et_al_2019_SaudiArabia",
    "summary": null,
    "translation": null,
    "pdf": "05_Alharbi_et_al_2019.pdf",
    "pdf_path": "02_Papers-goc/11-bai-ban-dau-va-mo-rong/05_Alharbi_et_al_2019.pdf",
    "topic": "Anxiety / mental health - Saudi Arabia",
    "set": "11-bai-ban-dau-va-mo-rong",
    "added": "2026-06-07",
    "note": "Bộ 11 bài ban đầu + mở rộng cho LA NCS Công Thị Hằng"
  },
  "BB06": {
    "id": "BB06",
    "descriptor": "Nakie_et_al_2022_Ethiopia",
    "summary": null,
    "translation": null,
    "pdf": "06_Nakie_et_al_2022.pdf",
    "pdf_path": "02_Papers-goc/11-bai-ban-dau-va-mo-rong/06_Nakie_et_al_2022.pdf",
    "topic": "Anxiety / depression - Ethiopia",
    "set": "11-bai-ban-dau-va-mo-rong",
    "added": "2026-06-07",
    "note": "Bộ 11 bài ban đầu + mở rộng cho LA NCS Công Thị Hằng"
  },
  "BB07": {
    "id": "BB07",
    "descriptor": "Chen_et_al_2023_China_BMCPsych",
    "summary": null,
    "translation": null,
    "pdf": "07_Chen_et_al_2023.pdf",
    "pdf_path": "02_Papers-goc/11-bai-ban-dau-va-mo-rong/07_Chen_et_al_2023.pdf",
    "topic": "Anxiety - China (BMC Psychiatry)",
    "set": "11-bai-ban-dau-va-mo-rong",
    "added": "2026-06-07",
    "note": "Bộ 11 bài ban đầu + mở rộng cho LA NCS Công Thị Hằng"
  },
  "BB08": {
    "id": "BB08",
    "descriptor": "Wen_et_al_2020_China_Rural",
    "summary": null,
    "translation": null,
    "pdf": "08_Wen_et_al_2020.pdf",
    "pdf_path": "02_Papers-goc/11-bai-ban-dau-va-mo-rong/08_Wen_et_al_2020.pdf",
    "topic": "Anxiety - rural China, latent profile analysis",
    "set": "11-bai-ban-dau-va-mo-rong",
    "added": "2026-06-07",
    "note": "Bộ 11 bài ban đầu + mở rộng cho LA NCS Công Thị Hằng"
  },
  "BB09": {
    "id": "BB09",
    "descriptor": "Qiu_et_al_2022_China_Parenting",
    "summary": null,
    "translation": null,
    "pdf": "09_Qiu_et_al_2022.pdf",
    "pdf_path": "02_Papers-goc/11-bai-ban-dau-va-mo-rong/09_Qiu_et_al_2022.pdf",
    "topic": "Anxiety & parenting - China",
    "set": "11-bai-ban-dau-va-mo-rong",
    "added": "2026-06-07",
    "note": "Bộ 11 bài ban đầu + mở rộng cho LA NCS Công Thị Hằng"
  },
  "BB10": {
    "id": "BB10",
    "descriptor": "Xu_2021_China_LargestEpi",
    "summary": null,
    "translation": null,
    "pdf": "QT010_Xu_2021_China_LargestEpi.pdf",
    "pdf_path": "02_Papers-goc/11-bai-ban-dau-va-mo-rong/QT010_Xu_2021_China_LargestEpi.pdf",
    "topic": "Largest anxiety epidemiology study - China",
    "set": "11-bai-ban-dau-va-mo-rong",
    "added": "2026-06-07",
    "note": "Bộ 11 bài ban đầu + mở rộng cho LA NCS Công Thị Hằng"
  },
  "BB11": {
    "id": "BB11",
    "descriptor": "Saikia_2023_IJCM",
    "summary": null,
    "translation": null,
    "pdf": "11_Saikia_2023_IJCM.pdf",
    "pdf_path": "02_Papers-goc/11-bai-ban-dau-va-mo-rong/11_Saikia_2023_IJCM.pdf",
    "topic": "Anxiety - India (Indian J Community Medicine)",
    "set": "11-bai-ban-dau-va-mo-rong",
    "added": "2026-06-07",
    "note": "Bộ 11 bài ban đầu + mở rộng cho LA NCS Công Thị Hằng"
  },
  "BB12": {
    "id": "BB12",
    "descriptor": "VNAMHS_2023_Vietnam",
    "summary": null,
    "translation": null,
    "pdf": "12_VNAMHS_2023.pdf",
    "pdf_path": "02_Papers-goc/11-bai-ban-dau-va-mo-rong/12_VNAMHS_2023.pdf",
    "topic": "Vietnam National Adolescent Mental Health Survey (VNAMHS) 2023",
    "set": "11-bai-ban-dau-va-mo-rong",
    "added": "2026-06-07",
    "note": "Bộ 11 bài ban đầu + mở rộng cho LA NCS Công Thị Hằng"
  },
  "BB14": {
    "id": "BB14",
    "descriptor": "Vietnam_COVID_DAS",
    "summary": null,
    "translation": null,
    "pdf": "14_Vietnam_COVID_DAS.pdf",
    "pdf_path": "02_Papers-goc/11-bai-ban-dau-va-mo-rong/14_Vietnam_COVID_DAS.pdf",
    "topic": "COVID-19 depression/anxiety/stress (DASS) - Vietnam",
    "set": "11-bai-ban-dau-va-mo-rong",
    "added": "2026-06-07",
    "note": "Bộ 11 bài ban đầu + mở rộng cho LA NCS Công Thị Hằng"
  },
  "BB18": {
    "id": "BB18",
    "descriptor": "Rising_Burden_2024",
    "summary": null,
    "translation": null,
    "pdf": "18_Rising_Burden_2024.pdf",
    "pdf_path": "02_Papers-goc/11-bai-ban-dau-va-mo-rong/18_Rising_Burden_2024.pdf",
    "topic": "Rising burden of anxiety/mental disorders - global 2024",
    "set": "11-bai-ban-dau-va-mo-rong",
    "added": "2026-06-07",
    "note": "Bộ 11 bài ban đầu + mở rộng cho LA NCS Công Thị Hằng"
  },
  "BB19": {
    "id": "BB19",
    "descriptor": "LMIC_Prevention_2024",
    "summary": null,
    "translation": null,
    "pdf": "19_LMIC_Prevention_2024.pdf",
    "pdf_path": "02_Papers-goc/11-bai-ban-dau-va-mo-rong/19_LMIC_Prevention_2024.pdf",
    "topic": "Prevention of anxiety in low- and middle-income countries (LMIC) 2024",
    "set": "11-bai-ban-dau-va-mo-rong",
    "added": "2026-06-07",
    "note": "Bộ 11 bài ban đầu + mở rộng cho LA NCS Công Thị Hằng"
  },
  "BB22": {
    "id": "BB22",
    "descriptor": "Nepal_2023",
    "summary": null,
    "translation": null,
    "pdf": "22_Nepal_2023.pdf",
    "pdf_path": "02_Papers-goc/11-bai-ban-dau-va-mo-rong/22_Nepal_2023.pdf",
    "topic": "Anxiety / mental health - Nepal 2023",
    "set": "11-bai-ban-dau-va-mo-rong",
    "added": "2026-06-07",
    "note": "Bộ 11 bài ban đầu + mở rộng cho LA NCS Công Thị Hằng"
  }
}
